Exemples/multiplexeur/multiplexeur.vhd
LIBRARY IEEE;
USE IEEE.STD_LOGIC_1164.ALL;

ENTITY multiplexer IS
	PORT (	E : IN STD_LOGIC_VECTOR(3 DOWNTO 0);
			C : IN STD_LOGIC_VECTOR(1 DOWNTO 0);
			S : OUT STD_LOGIC);
END ENTITY multiplexer;


ARCHITECTURE fdd_MPX OF multiplexer IS
BEGIN
	WITH C SELECT
		S <= 	E(0) WHEN "00",
				E(1) WHEN "01",
				E(2) WHEN "10",
				E(3) WHEN "11",
				'X' WHEN OTHERS;
END ARCHITECTURE fdd_MPX;

Exemples/multiplexeur/testbench.vhd
LIBRARY IEEE;
USE IEEE.STD_LOGIC_1164.all;
USE IEEE.NUMERIC_STD.ALL;

ENTITY test IS
END ENTITY;

ARCHITECTURE arc OF test IS

	SIGNAL I : STD_LOGIC_VECTOR(3 DOWNTO 0);
	SIGNAL C : STD_LOGIC_VECTOR(1 DOWNTO 0);
	SIGNAL S : STD_LOGIC;

	COMPONENT multiplexer IS
		PORT (	E : IN STD_LOGIC_VECTOR(3 DOWNTO 0);
				C : IN STD_LOGIC_VECTOR(1 DOWNTO 0);
				S : OUT STD_LOGIC);
		END COMPONENT;

BEGIN
	-- test du multiplexeur
	fddMPX : multiplexer PORT MAP (I, C, S);
	I(3) <= '0', '1' AFTER 30 ns, '0' AFTER 40 ns, '1' AFTER 70 ns, '0' AFTER 80 ns, '1' AFTER 110 ns, '0' AFTER 120 ns, '1' AFTER 150 ns, '0' AFTER 160 ns;
	I(2) <= '0', '1' AFTER 20 ns, '0' AFTER 30 ns, '1' AFTER 60 ns, '0' AFTER 70 ns, '1' AFTER 100 ns, '0' AFTER 110 ns, '1' AFTER 140 ns, '0' AFTER 150 ns;
	I(1) <= '0', '1' AFTER 10 ns, '0' AFTER 20 ns, '1' AFTER 50 ns, '0' AFTER 60 ns, '1' AFTER 90 ns, '0' AFTER 100 ns, '1' AFTER 130 ns, '0' AFTER 140 ns;
	I(0) <= '1', '0' AFTER 10 ns, '1' AFTER 40 ns, '0' AFTER 50 ns, '1' AFTER 80 ns, '0' AFTER 90 ns, '1' AFTER 120 ns, '0' AFTER 130 ns;
	C(1) <= '0', '1' AFTER 80 ns, '0' AFTER 160 ns;
	C(0) <= '0', '1' AFTER 40 ns, '0' AFTER 80 ns, '1' AFTER 120 ns;

END ARCHITECTURE;

Exemples/multiplexeur/test.vcd
$date
  Mon Oct 19 09:58:53 2020
$end
$version
  GHDL v0
$end
$timescale
  1 fs
$end
$scope module standard $end
$upscope $end
$scope module std_logic_1164 $end
$upscope $end
$scope module numeric_std $end
$upscope $end
$scope module test $end
$var reg 4 ! i[3:0] $end
$var reg 2 " c[1:0] $end
$var reg 1 # s $end
$scope module fddmpx $end
$var reg 4 $ e[3:0] $end
$var reg 2 % c[1:0] $end
$var reg 1 & s $end
$upscope $end
$upscope $end
$enddefinitions $end
#0
b0001 !
b00 "
1#
b0001 $
b00 %
1&
#10000000
b0010 !
0#
b0010 $
0&
#20000000
b0100 !
b0100 $
#30000000
b1000 !
b1000 $
#40000000
b0001 !
b01 "
b0001 $
b01 %
#50000000
b0010 !
1#
b0010 $
1&
#60000000
b0100 !
0#
b0100 $
0&
#70000000
b1000 !
b1000 $
#80000000
b0001 !
b10 "
b0001 $
b10 %
#90000000
b0010 !
b0010 $
#100000000
b0100 !
1#
b0100 $
1&
#110000000
b1000 !
0#
b1000 $
0&
#120000000
b0001 !
b11 "
b0001 $
b11 %
#130000000
b0010 !
b0010 $
#140000000
b0100 !
b0100 $
#150000000
b1000 !
1#
b1000 $
1&
#160000000
b0000 !
b01 "
0#
b0000 $
b01 %
0&
